{"name":"Kinglert.GitHub.io","tagline":"test home page","body":"#Welcome to My Github  \r\n![](https://scontent-a-hkg.xx.fbcdn.net/hphotos-xpa1/v/t1.0-9/10906195_748301865223312_4778585448919108682_n.jpg?oh=e919e5813f084b8885496a6fbfdf29e9&oe=555FCCE0)\r\n\r\n##My Resume\r\n\r\nName : Tharit Lertpakdeewong  \r\nNickname : King  \r\nBirth : 13 June 1994  \r\nAge : 20   \r\nGender : Male  \r\nJob : Student  \r\nEducation :  Faculty of Management Science  \r\nUniversity : Prince of Songkla University\r\n\r\n\r\n","google":"","note":"Don't delete this file! It's used internally to help with page regeneration."}